Automan
