Metadata-Version: 1.0
Name: MyAutoman
Version: 1.7.3
Summary: Automan
Home-page: UNKNOWN
Author: wwj&zqy
Author-email: wangwenjie@smyfinancial.com
License: BSD License
Platform: UNKNOWN
